repo_to_text/__init__.py
repo_to_text/main.py
repo_to_text/cli/__init__.py
repo_to_text/cli/cli.py
repo_to_text/core/__init__.py
repo_to_text/core/core.py
repo_to_text/utils/__init__.py
repo_to_text/utils/utils.py
repo_to_text-1.0.0.dist-info/METADATA
repo_to_text-1.0.0.dist-info/WHEEL
repo_to_text-1.0.0.dist-info/entry_points.txt
repo_to_text-1.0.0.dist-info/licenses/LICENSE
repo_to_text-1.0.0.dist-info/RECORD
