Metadata-Version: 2.4
Name: repo-to-text
Version: 1.0.0
Summary: Convert a directory structure and its contents into a single text file, including the tree output and file contents in structured XML format. It may be useful to chat with LLM about your code.
Project-URL: Homepage, https://github.com/kirill-markin/repo-to-text
Project-URL: Repository, https://github.com/kirill-markin/repo-to-text
Author-email: Kirill Markin <markinkirill@gmail.com>
License: MIT
License-File: LICENSE
Classifier: Development Status :: 4 - Beta
Classifier: License :: OSI Approved :: MIT License
Classifier: Operating System :: OS Independent
Classifier: Programming Language :: Python :: 3
Requires-Python: >=3.9
Requires-Dist: argparse>=1.4.0
Requires-Dist: pathspec>=0.12.1
Requires-Dist: pyyaml>=6.0.1
Requires-Dist: setuptools>=70.0.0
Provides-Extra: dev
Requires-Dist: black; extra == 'dev'
Requires-Dist: build; extra == 'dev'
Requires-Dist: isort; extra == 'dev'
Requires-Dist: mypy; extra == 'dev'
Requires-Dist: pylint; extra == 'dev'
Requires-Dist: pytest>=8.2.2; extra == 'dev'
Requires-Dist: twine; extra == 'dev'
